Mensajes/__init__.py
Mensajes/adios/__init__.py
Mensajes/adios/despedir.py
Mensajes/subpaquete/__init__.py
Mensajes/subpaquete/saludos.py
tests/__init__.py
tests/test_hola.py
Mensajes_Panchob28-5.0.dist-info/LICENSE
Mensajes_Panchob28-5.0.dist-info/METADATA
Mensajes_Panchob28-5.0.dist-info/WHEEL
Mensajes_Panchob28-5.0.dist-info/top_level.txt
Mensajes_Panchob28-5.0.dist-info/RECORD
