Metadata-Version: 2.1
Name: Mensajes-Panchob28
Version: 5.0
Home-page: https://www.linkedin.com/in/francisco-burchardt/
License-File: LICENSE
Requires-Dist: numpy ==1.26.2
